LICENSE
MANIFEST.in
README.md
setup.py
fiscalmodel/__init__.py
fiscalmodel/util.py
fiscalmodel.egg-info/PKG-INFO
fiscalmodel.egg-info/SOURCES.txt
fiscalmodel.egg-info/dependency_links.txt
fiscalmodel.egg-info/pbr.json
fiscalmodel.egg-info/requires.txt
fiscalmodel.egg-info/top_level.txt
fiscalmodel.egg-info/zip-safe
fiscalmodel/data/countries.csv
fiscalmodel/data/currency.json
fiscalmodel/data/language.json
test/test_currency.py