Metadata-Version: 1.1
Name: fiscalmodel
Version: 0.1.1
Summary: Reference data for fiscal data classification
Home-page: http://github.com/pudo/fiscalmodel
Author: Friedrich Lindenberg
Author-email: friedrich@pudo.org
License: MIT
Keywords: reference data budgets spending revenue fiscal
Platform: UNKNOWN
Classifier: Development Status :: 3 - Alpha
Classifier: Intended Audience :: Developers
Classifier: License :: OSI Approved :: MIT License
Classifier: Operating System :: OS Independent
Classifier: Programming Language :: Python :: 2.7
